fastbf.py
fast_brainfuck-3.0.1.dist-info/METADATA
fast_brainfuck-3.0.1.dist-info/WHEEL
fast_brainfuck-3.0.1.dist-info/entry_points.txt
fast_brainfuck-3.0.1.dist-info/top_level.txt
fast_brainfuck-3.0.1.dist-info/RECORD
