Metadata-Version: 2.1
Name: fast-brainfuck
Version: 3.0.1
Summary: Brainfuck "compiler" for Python (fast)
Home-page: https://github.com/none-None1/fast-bf
License: UNKNOWN
Keywords: brainfuck
Platform: UNKNOWN
Classifier: Programming Language :: C++
Classifier: Operating System :: Microsoft :: Windows
Classifier: Operating System :: Unix
Classifier: Programming Language :: Python :: 3 :: Only
Classifier: Programming Language :: Python :: Implementation :: CPython
Classifier: Programming Language :: Python :: Implementation :: PyPy
Classifier: Topic :: Software Development :: Compilers
Classifier: Topic :: Software Development :: Code Generators
Classifier: Topic :: Software Development :: Libraries :: Python Modules
Classifier: Development Status :: 6 - Mature
Requires-Python: >=3.6
Requires-Dist: pybind11
Requires-Dist: setuptools
